miniirc_extras/__init__.py
miniirc_extras/_classes.py
miniirc_extras/_numerics.py
miniirc_extras/_require.py
miniirc_extras/aioirc.py
miniirc_extras/bot.py
miniirc_extras/formatting.py
miniirc_extras/utils.py
miniirc_extras/features/__init__.py
miniirc_extras/features/_json.py
miniirc_extras/features/chans.py
miniirc_extras/features/ensure_connection.py
miniirc_extras/features/mp.py
miniirc_extras/features/testfeature.py
miniirc_extras/features/users.py
miniirc_extras-0.3.4.dist-info/LICENSE.md
miniirc_extras-0.3.4.dist-info/METADATA
miniirc_extras-0.3.4.dist-info/WHEEL
miniirc_extras-0.3.4.dist-info/top_level.txt
miniirc_extras-0.3.4.dist-info/RECORD
