Metadata-Version: 2.1
Name: miniirc-extras
Version: 0.3.4
Summary: WIP extensions for miniirc.
Home-page: https://github.com/luk3yx/miniirc_extras
Author: luk3yx
License: MIT
Platform: UNKNOWN
Classifier: Development Status :: 4 - Beta
Classifier: License :: OSI Approved :: MIT License
Classifier: Operating System :: OS Independent
Classifier: Programming Language :: Python :: 3
Classifier: Programming Language :: Python :: 3.5
Classifier: Programming Language :: Python :: 3.6
Classifier: Programming Language :: Python :: 3.7
Classifier: Programming Language :: Python :: 3.8
Classifier: Topic :: Software Development :: Libraries
Requires-Python: >=3.5
Requires-Dist: miniirc (>=1.4.3)
Requires-Dist: deprecated (<2,>=1.2.5)
